BitcoinPrice/Bitcoin_Price.py
Bitcoin_Price-0.3.dist-info/LICENSE
Bitcoin_Price-0.3.dist-info/METADATA
Bitcoin_Price-0.3.dist-info/WHEEL
Bitcoin_Price-0.3.dist-info/entry_points.txt
Bitcoin_Price-0.3.dist-info/top_level.txt
Bitcoin_Price-0.3.dist-info/RECORD
