Metadata-Version: 2.1
Name: Bitcoin-Price
Version: 0.3
Summary: A package for bitcoin price notification in telegram
Home-page: UNKNOWN
Author: Abhishek Asarawa
Author-email: aasarawa@gmail.com
License: MIT
Platform: UNKNOWN
Classifier: Programming Language :: Python :: 3
Requires-Dist: requests
